dj_authentication/__init__.py
dj_authentication/_util.py
dj_authentication/apps.py
dj_authentication/openid.py
dj_authentication/request_http_auth.py
dj_authentication/request_user.py
dj_authentication/user_mappings.py
dj_authentication/methods/__init__.py
dj_authentication/methods/basic.py
dj_authentication/methods/bearer.py
dj_authentication-0.2.0.dist-info/LICENSE
dj_authentication-0.2.0.dist-info/METADATA
dj_authentication-0.2.0.dist-info/WHEEL
dj_authentication-0.2.0.dist-info/top_level.txt
dj_authentication-0.2.0.dist-info/zip-safe
dj_authentication-0.2.0.dist-info/RECORD
