Metadata-Version: 2.1
Name: dj-authentication
Version: 0.2.0
Summary: Nice HTTP authentication support for Django
Home-page: https://gitlab.com/aiakos/dj-authentication
Author: Aiakos Contributors
Author-email: aiakos@aiakosauth.com
License: UNKNOWN
Keywords: http auth authentication basic www-authenticate
Platform: UNKNOWN
Classifier: Development Status :: 4 - Beta
Classifier: Intended Audience :: Developers
Classifier: Topic :: System :: Systems Administration :: Authentication/Directory
Classifier: License :: OSI Approved :: MIT License
Classifier: Programming Language :: Python :: 3
Classifier: Programming Language :: Python :: 3 :: Only
Classifier: Programming Language :: Python :: 3.4
Classifier: Programming Language :: Python :: 3.5
Classifier: Programming Language :: Python :: 3.6
Classifier: Programming Language :: Python :: 3.7
Classifier: Framework :: Django
Classifier: Framework :: Django :: 2.0
Classifier: Framework :: Django :: 2.1
Requires-Dist: django (>=2.0.0)
Requires-Dist: openid-connect (>=0.5.0)
Requires-Dist: dj12 (>=0.3.0)
